LICENSE
MANIFEST.in
README
setup.py
django_oauth_twitter/__init__.py
django_oauth_twitter/admin.py
django_oauth_twitter/cache.py
django_oauth_twitter/context_processors.py
django_oauth_twitter/forms.py
django_oauth_twitter/middleware.py
django_oauth_twitter/models.py
django_oauth_twitter/signals.py
django_oauth_twitter/test_urls.py
django_oauth_twitter/tests.py
django_oauth_twitter/utils.py
django_oauth_twitter/views.py
django_oauth_twitter.egg-info/PKG-INFO
django_oauth_twitter.egg-info/SOURCES.txt
django_oauth_twitter.egg-info/dependency_links.txt
django_oauth_twitter.egg-info/top_level.txt
django_oauth_twitter.egg-info/zip-safe
django_oauth_twitter/migrations/0001_initial.py
django_oauth_twitter/migrations/__init__.py
django_oauth_twitter/templates/django_oauth_twitter/associate.html
django_oauth_twitter/templates/django_oauth_twitter/register.html