Metadata-Version: 1.1
Name: django-oauth-twitter
Version: 1.11
Summary: A Django application that lets you associate Twitter accounts with your User accounts
Home-page: http://bitbucket.org/akoha/django-oauth-twitter/
Author: Akoha Inc.
Author-email: adminmail@akoha.com
License: UNKNOWN
Platform: UNKNOWN
Classifier: Development Status :: 5 - Production/Stable
Classifier: Environment :: Web Environment
Classifier: Framework :: Django
Classifier: License :: OSI Approved :: MIT License
Classifier: Operating System :: OS Independent
Classifier: Programming Language :: Python
Requires: oauth
Requires: oauth_python_twitter
